[
    {
        "id": "sl1090483407",
        "isLive": true,
        "event": "Football Blockbusters 24x7",
        "match": "",
        "Provider": "SonyLiv",
        "poster": "https://origin-staticv2.sonyliv.com/videoasset_images/manage_file/1000004282/1749885060000461_Football_Blockbusters_24x7_landscape_thumb_14jun.jpg",
        "genre": "Football",
        "language": "ENG",
        "venue": "N/A",
        "TVchannel": "LIV",
        "MaxResolution": "FHD",
        "SeoTags": "UCL,UEFA Champions League,UEL,UEFA Europa League,UNL,UEFA Nations League,FA Cup,live sports,Sony LIV,football streaming,soccer live,sports tournaments,live matches,sports highlights,football news,soccer updates,live football,sports schedule,match replays,sports analysis,football fixtures,soccer scores,live commentary,sports coverage,football fans,soccer lovers,sports events,live streaming,sports app,Sony sports",
        "Server1": "?hdnea=exp=1750513321~acl=/*~id=10141772583125824661732517230917~hmac=6b7bacef4d0ebf545e039db78183a6f4eb87a4657ccba31ecad89cbd1be8e453",
        "Server2": "?hdnea=exp=1750513321~acl=/*~id=10141772583125824661732517230917~hmac=6b7bacef4d0ebf545e039db78183a6f4eb87a4657ccba31ecad89cbd1be8e453",
        "Server3": "?hdnea=exp=1750513321~acl=/*~id=10141772583125824661732517230917~hmac=6b7bacef4d0ebf545e039db78183a6f4eb87a4657ccba31ecad89cbd1be8e453"
    }
]